financial_analyzer/__init__.py
financial_analyzer/breakeven_point.py
financial_analyzer/plot_breakeven_point.py
financial_analyzer/roi.py
financial_analyzer/units_for_target_profit.py
financial_analyzer-0.2.4.dist-info/LICENSE
financial_analyzer-0.2.4.dist-info/METADATA
financial_analyzer-0.2.4.dist-info/WHEEL
financial_analyzer-0.2.4.dist-info/RECORD
