Metadata-Version: 2.1
Name: financial_analyzer
Version: 0.2.4
Summary: Calculate basic metrics of sales data and visualize the results.
License: MIT
Author: Nicole Tu, Rafe Chang, Alan PowPowichrowski, Chris Gao
Requires-Python: >=3.9
Classifier: License :: OSI Approved :: MIT License
Classifier: Programming Language :: Python :: 3
Classifier: Programming Language :: Python :: 3.9
Classifier: Programming Language :: Python :: 3.10
Classifier: Programming Language :: Python :: 3.11
Classifier: Programming Language :: Python :: 3.12
Requires-Dist: altair (>=5.2.0)
Requires-Dist: numpy (>=1.26.3)
Requires-Dist: pandas (>=2.2.0)
